yta_video_utils/__init__.py
yta_video_utils/audio.py
yta_video_utils/combination.py
yta_video_utils/concatenation.py
yta_video_utils/dimensions.py
yta_video_utils/duration.py
yta_video_utils/generation.py
yta_video_utils/mask.py
yta_video_utils/resize.py
yta_video_utils/subclip.py
yta_video_utils/validation.py
yta_video_utils-0.0.10.dist-info/licenses/LICENSE
yta_video_utils-0.0.10.dist-info/METADATA
yta_video_utils-0.0.10.dist-info/WHEEL
yta_video_utils-0.0.10.dist-info/RECORD
