Metadata-Version: 2.4
Name: yta-video-utils
Version: 0.0.10
Summary: Youtube Autonomous Video Utils Module (@deprecated?)
License-File: LICENSE
Author: danialcala94
Author-email: danielalcalavalera@gmail.com
Requires-Python: ==3.9
Classifier: Programming Language :: Python :: 3
Classifier: Programming Language :: Python :: 3.9
Requires-Dist: ffmpeg-python (>=0.0.1,<9.0.0)
Requires-Dist: moviepy (>=0.0.1,<9.0.0)
Requires-Dist: yta_constants (>=0.0.1,<1.0.0)
Requires-Dist: yta_file (>=0.0.1,<1.0.0)
Requires-Dist: yta_image_base (>=0.0.1,<1.0.0)
Requires-Dist: yta_image_utils (>=0.0.1,<1.0.0)
Requires-Dist: yta_positioning (>=0.0.1,<1.0.0)
Requires-Dist: yta_programming (>=0.0.1,<1.0.0)
Requires-Dist: yta_validation (>=0.0.1,<1.0.0)
Requires-Dist: yta_video_moviepy (>=0.0.1,<1.0.0)
